MEALY_MACHINE/mealy_machine_001.v
module mealy_machine_001(det,inp,clk,reset);
  input clk,reset,inp;
  output reg det;
  parameter s0=2'b00,s1=2'b01,s2=2'b10;
  reg [1:0] pr_state,nxt_state;
//   sequantial 
  always@(posedge clk)
    if(reset)
      pr_state <= s0;
  	else 
      pr_state <= nxt_state;
//   combinational
  always @(*)
    case(pr_state)
      s0:begin 
        if (inp)
           nxt_state = s0;
        else nxt_state= s1;
          det=0;
      end
      // s1:if (inp) nxt_state = s0;
      //   else nxt_state= s2;
      s1:begin 
        if (inp)
           nxt_state = s0;
        else nxt_state= s2;
          det=0;
      end
      s2:begin 
        if (inp)begin
           nxt_state = s0;
           det=1;
        end
        else nxt_state= s2;   
      end
      default: begin
      nxt_state= s0;
      det=0;
      end
     endcase

endmodule

MEALY_MACHINE/mealy_machine_001_tb.v
`timescale 1ns/1ns
`include "mealy_machine_001.v"
module mealy_machine_001_tb;
reg inp, clk,reset;
wire det;
 mealy_machine_001 mealy_machine_001_1 (
    .det(det),
    .inp(inp),
    .clk(clk),
    .reset(reset)
  );
always #5 clk =~clk;
  initial begin 
  $dumpfile("mealy_machine_001.vcd");
  $dumpvars(0,mealy_machine_001_tb);
    $monitor("Time=%0t | reset = %b |inp=%b | det=%b | state=%b", $time,reset, inp, det, mealy_machine_001_1.pr_state);
  clk= 0;
  reset=1;
  inp = 0;
      // Release reset after 10sec reset = 0
    #10 reset = 0;
   // Sequence: 0 0 1 0 0 1 1
   #10 inp = 0;
   #10 inp = 0;
   #10 inp = 1;
   #10 inp = 0;
   #10 inp = 0;
   #10 inp = 1;
   #10 inp = 1;
   #10 $finish;
   end
   endmodule

MEALY_MACHINE/mealy_machine_001.vcd
$date
	Tue Oct 21 10:37:43 2025
$end
$version
	Icarus Verilog
$end
$timescale
	1ns
$end
$scope module mealy_machine_001_tb $end
$var wire 1 ! det $end
$var reg 1 " clk $end
$var reg 1 # inp $end
$var reg 1 $ reset $end
$scope module mealy_machine_001_1 $end
$var wire 1 " clk $end
$var wire 1 # inp $end
$var wire 1 $ reset $end
$var parameter 2 % s0 $end
$var parameter 2 & s1 $end
$var parameter 2 ' s2 $end
$var reg 1 ! det $end
$var reg 2 ( nxt_state [1:0] $end
$var reg 2 ) pr_state [1:0] $end
$upscope $end
$upscope $end
$enddefinitions $end
$comment Show the parameter values. $end
$dumpall
b10 '
b1 &
b0 %
$end
#0
$dumpvars
bx )
b0 (
1$
0#
0"
0!
$end
#5
b1 (
b0 )
1"
#10
0"
0$
#15
b10 (
b1 )
1"
#20
0"
#25
b10 )
1"
#30
0"
#35
1"
#40
1!
b0 (
0"
1#
#45
0!
b0 )
1"
#50
b1 (
0"
0#
#55
b10 (
b1 )
1"
#60
0"
#65
b10 )
1"
#70
1!
b0 (
0"
1#
#75
0!
b0 )
1"
